[ 
    {
      "id":1,
      "name": "Story Book",
      "title":"Lorem, ipsum dolor sit amet consectetur adipisicing elit",
      "category":"Free",
      "price":0,
      "image":"https://img.freepik.com/free-vector/hand-drawn-flat-design-stack-books-illustration_23-2149341898.jpg?ga=GA1.1.1396062440.1720103974&semt=sph"


    },

    
    {
        "id":2,
        "name": "Sports Book",
        "title":"Lorem, ipsum dolor sit amet consectetur adipisicing elit",
        "category":"Free",
        "price":0,
        "image":"https://img.freepik.com/free-vector/hand-drawn-flat-design-stack-books-illustration_23-2149341898.jpg?ga=GA1.1.1396062440.1720103974&semt=sph"
  
  
      },
      
    {
        "id":3,
        "name": "music Book",
        "title":"Lorem, ipsum dolor sit amet consectetur adipisicing elit",
        "category":"Music",
        "price":200,
        "image":"https://img.freepik.com/free-vector/hand-drawn-flat-design-stack-books-illustration_23-2149341898.jpg?ga=GA1.1.1396062440.1720103974&semt=sph"
  
  
      },

      
    {
        "id":4,
        "name": "Improv Book",
        "title":"Lorem, ipsum dolor sit amet consectetur adipisicing elit",
        "category":"Free",
        "price":0,
        "image":"https://img.freepik.com/free-vector/hand-drawn-flat-design-stack-books-illustration_23-2149341898.jpg?ga=GA1.1.1396062440.1720103974&semt=sph"
  
  
      },

      
    {
        "id":5,
        "name": "Business Book",
        "title":"Lorem, ipsum dolor sit amet consectetur adipisicing elit",
        "category":"Business",
        "price":300,
        "image":"https://img.freepik.com/free-vector/hand-drawn-flat-design-stack-books-illustration_23-2149341898.jpg?ga=GA1.1.1396062440.1720103974&semt=sph"
  
  
      },

      
    {
        "id":6,
        "name": "History Book",
        "title":"Lorem, ipsum dolor sit amet consectetur adipisicing elit",
        "category":"Free",
        "price":0,
        "image":"https://img.freepik.com/free-vector/hand-drawn-flat-design-stack-books-illustration_23-2149341898.jpg?ga=GA1.1.1396062440.1720103974&semt=sph"
  
  
      },
      
    {
        "id":7,
        "name": "Althletics Book",
        "title":"Lorem, ipsum dolor sit amet consectetur adipisicing elit",
        "category":"Sports",
        "price":110,
        "image":"https://img.freepik.com/free-vector/hand-drawn-flat-design-stack-books-illustration_23-2149341898.jpg?ga=GA1.1.1396062440.1720103974&semt=sph"
  
  
      },

      
    {
        "id":8,
        "name": "philosophy Book",
        "title":"Lorem, ipsum dolor sit amet consectetur adipisicing elit",
        "category":"Free",
        "price":0,
        "image":"https://img.freepik.com/free-vector/hand-drawn-flat-design-stack-books-illustration_23-2149341898.jpg?ga=GA1.1.1396062440.1720103974&semt=sph"
  
  
      },

      
    {
        "id":9,
        "name": "waterlife Book",
        "title":"Lorem, ipsum dolor sit amet consectetur adipisicing elit",
        "category":"Free",
        "price":0,
        "image":"https://img.freepik.com/free-vector/hand-drawn-flat-design-stack-books-illustration_23-2149341898.jpg?ga=GA1.1.1396062440.1720103974&semt=sph"
  
  
      },
      
    {
        "id":10,
        "name": "Cooking Book",
        "title":"Lorem, ipsum dolor sit amet consectetur adipisicing elit",
        "category":"Free",
        "price":0,
        "image":"https://img.freepik.com/free-vector/hand-drawn-flat-design-stack-books-illustration_23-2149341898.jpg?ga=GA1.1.1396062440.1720103974&semt=sph"
  
  
      }




]